{
  "kind": "collectionType",
  "collectionName": "quarters",
  "info": {
    "singularName": "quarter",
    "pluralName": "quarters",
    "displayName": "Quarter",
    "description": ""
  },
  "options": {
    "draftAndPublish": true
  },
  "pluginOptions": {
    "i18n": {
      "localized": true
    }
  },
  "attributes": {
    "name": {
      "type": "string",
      "required": true,
      "pluginOptions": {
        "i18n": {
          "localized": true
        }
      }
    },
    "description": {
      "type": "text",
      "pluginOptions": {
        "i18n": {
          "localized": true
        }
      }
    },
    "color": {
      "type": "enumeration",
      "enum": [
        "yellow",
        "green",
        "pink",
        "blue"
      ],
      "required": true
    }
  }
}
